setup.py
mail_lib/__init__.py
mail_lib/mail_utils.py
mail_lib.egg-info/PKG-INFO
mail_lib.egg-info/SOURCES.txt
mail_lib.egg-info/dependency_links.txt
mail_lib.egg-info/requires.txt
mail_lib.egg-info/top_level.txt