Metadata-Version: 1.0
Name: mail-lib
Version: 1.0.0
Summary: Mail Library
Home-page: https://github.com/Akira-Taniguchi/mail_lib
Author: AkiraTaniguchi
Author-email: dededededaiou2003@yahoo.co.jp
License: MIT
Keywords: mail send smtp address attach
Platform: UNKNOWN
Classifier: Development Status :: 5 - Production/Stable
Classifier: Programming Language :: Python :: 2.7
Classifier: Intended Audience :: Developers
Classifier: License :: OSI Approved :: MIT License
